sparkcleaner/__init__.py
sparkcleaner/functions/__init__.py
sparkcleaner/functions/string_cleaning.py
sparkcleaner/functions/type_cast.py
sparkcleaner/helpers/__init__.py
sparkcleaner/helpers/example_data.py
sparkcleaner/helpers/verify.py
sparkcleaner-1.1.1.dist-info/LICENSE
sparkcleaner-1.1.1.dist-info/METADATA
sparkcleaner-1.1.1.dist-info/WHEEL
sparkcleaner-1.1.1.dist-info/top_level.txt
sparkcleaner-1.1.1.dist-info/RECORD
