Metadata-Version: 2.1
Name: sparkcleaner
Version: 1.1.1
Summary: cleaning functions for pyspark df
Home-page: https://github.com/IvoWnds/pysparkdfcleaner
Author: IvoW
Author-email: ivownds@gmail.com
License: UNKNOWN
Project-URL: Bug Tracker, https://github.com/IvoWnds/pysparkdfcleaner/issues
Platform: UNKNOWN
Classifier: Programming Language :: Python :: 3
Classifier: License :: OSI Approved :: MIT License
Classifier: Operating System :: OS Independent
Requires-Python: >=3.6
License-File: LICENSE
